page_scrapers/__init__.py
page_scrapers/wikipedia/__init__.py
page_scrapers/wikipedia/exceptions.py
page_scrapers/wikipedia/utils.py
page_scrapers/wikipedia/filters/__init__.py
page_scrapers/wikipedia/filters/base.py
page_scrapers/wikipedia/filters/film.py
page_scrapers/wikipedia/scrapers/__init__.py
page_scrapers/wikipedia/scrapers/base.py
page_scrapers/wikipedia/scrapers/film.py
page_scrapers-2.3.0.dist-info/LICENSE.txt
page_scrapers-2.3.0.dist-info/METADATA
page_scrapers-2.3.0.dist-info/WHEEL
page_scrapers-2.3.0.dist-info/top_level.txt
page_scrapers-2.3.0.dist-info/RECORD
