Metadata-Version: 2.1
Name: page-scrapers
Version: 2.3.0
Summary: Scrapers for specific websites
Home-page: https://www.alexseitsinger.com/packages/python/page-scrapers
Author: Alex Seitsinger
Author-email: software@alexseitsinger.com
License: BSD 2-Clause License
Project-URL: Documentation, https://www.alexseitsinger.com/packages/python/page-scrapers
Project-URL: Source, https://github.com/alexseitsinger/page-scrapers
Project-URL: Tracker, https://github.com/alexseitsinger/page-scrapers/issues
Keywords: web scrapers,wikipedia
Platform: UNKNOWN
Classifier: Development Status :: 5 - Production/Stable
Classifier: Environment :: Console
Classifier: Environment :: Web Environment
Classifier: Intended Audience :: Developers
Classifier: License :: OSI Approved :: BSD License
Classifier: Natural Language :: English
Classifier: Operating System :: OS Independent
Classifier: Programming Language :: Python :: 2
Classifier: Programming Language :: Python :: 3
Classifier: Topic :: Text Processing :: Markup :: HTML
Classifier: Topic :: Utilities
Requires-Dist: requests
Requires-Dist: bs4
Requires-Dist: text-tools
Requires-Dist: number-tools
